SAPsim/__init__.py
SAPsim/utils/__init__.py
SAPsim/utils/exceptions.py
SAPsim/utils/execute.py
SAPsim/utils/global_vars.py
SAPsim/utils/helpers.py
SAPsim/utils/instructions.py
SAPsim/utils/parser.py
tests/__init__.py
tests/test_SAPsim.py
tests/test_example_progs.py
tests/test_exceptions.py
tests/test_helpers.py
tests/test_instructions.py
SAPsim-1.1.1.dist-info/LICENSE
SAPsim-1.1.1.dist-info/METADATA
SAPsim-1.1.1.dist-info/WHEEL
SAPsim-1.1.1.dist-info/top_level.txt
SAPsim-1.1.1.dist-info/RECORD
