Metadata-Version: 2.1
Name: SAPsim
Version: 1.1.1
Summary: Simulation of SAP (Simple As Possible) computer programs from COMP311 (Computer Organization) @ UNC
Home-page: https://github.com/jesse-wei/SAPsim
Download-URL: https://github.com/jesse-wei/SAPsim/releases
Author: Jesse Wei
Author-email: Jesse Wei <jesse@cs.unc.edu>
Project-URL: Homepage, https://github.com/jesse-wei/SAPsim
Project-URL: Bug Tracker, https://github.com/jesse-wei/SAPsim/issues
Keywords: SAP,SAPsim,simple as possible,UNC,COMP311
Classifier: Programming Language :: Python :: 3
Classifier: License :: OSI Approved :: MIT License
Classifier: Operating System :: OS Independent
Classifier: Intended Audience :: Developers
Classifier: Topic :: Software Development :: Libraries :: Python Modules
Requires-Python: >=3.9
License-File: LICENSE
Requires-Dist: setuptools
Requires-Dist: tabulate
Requires-Dist: bidict
